aiobotocore/__init__.py
aiobotocore/args.py
aiobotocore/client.py
aiobotocore/config.py
aiobotocore/endpoint.py
aiobotocore/paginate.py
aiobotocore/session.py
aiobotocore_botorange-0.1.0.dist-info/DESCRIPTION.rst
aiobotocore_botorange-0.1.0.dist-info/METADATA
aiobotocore_botorange-0.1.0.dist-info/RECORD
aiobotocore_botorange-0.1.0.dist-info/WHEEL
aiobotocore_botorange-0.1.0.dist-info/metadata.json
aiobotocore_botorange-0.1.0.dist-info/top_level.txt
