Metadata-Version: 2.0
Name: aiobotocore-botorange
Version: 0.1.0
Summary: Async client for aws services using botocore and aiohttp
Home-page: https://github.com/aio-libs/aiobotocore
Author: Nikolay Novik
Author-email: nickolainovik@gmail.com
License: Apache 2
Download-URL: https://pypi.python.org/pypi/aiobotocore
Platform: UNKNOWN
Classifier: Intended Audience :: Developers
Classifier: Intended Audience :: System Administrators
Classifier: Programming Language :: Python :: 3
Classifier: Programming Language :: Python :: 3.4
Classifier: Programming Language :: Python :: 3.5
Classifier: Environment :: Web Environment
Classifier: Development Status :: 3 - Alpha
Requires-Dist: aiohttp (>=1.2.0,<2.0.0)
Requires-Dist: botocore (<2.0.0,>=1.5)
